poetrytestsqeddy/__init__.py
poetrytestsqeddy/testEddySemQuest.py
poetrytestsqeddy-0.2.3.dist-info/WHEEL
poetrytestsqeddy-0.2.3.dist-info/METADATA
poetrytestsqeddy-0.2.3.dist-info/RECORD
