Metadata-Version: 2.1
Name: poetrytestsqeddy
Version: 0.2.3
Summary: This is a test to see if Poetry works for the task.
Author: Eddy Ferrara Jr.
Author-email: e.ferrara@semquest.com
Requires-Python: >=3.8,<4.0
Classifier: Programming Language :: Python :: 3
Classifier: Programming Language :: Python :: 3.8
Requires-Dist: matplotlib (>=3.2.1,<4.0.0)
